spyrja/__init__.py
spyrja/common.py
spyrja/dict.py
spyrja/errors.py
spyrja/external.py
spyrja/idlist.py
spyrja/list.py
spyrja/set.py
spyrja-0.1.0.dist-info/METADATA
spyrja-0.1.0.dist-info/WHEEL
spyrja-0.1.0.dist-info/top_level.txt
spyrja-0.1.0.dist-info/RECORD
