Metadata-Version: 2.1
Name: spyrja
Version: 0.1.0
Summary: Query functions for collections of namedtuples
Home-page: http://gitlab.com/OldIronHorse/spyrja
Author: Simon Redding
Author-email: s1m0n.r3dd1ng@gmail.com
License: GPL3
Platform: UNKNOWN
Requires-Python: >=3.7
